iplogger/__init__.py
iplogger/admin.py
iplogger/apps.py
iplogger/middleware.py
iplogger/models.py
django_dc_iplogger-0.3.0.dist-info/LICENSE
django_dc_iplogger-0.3.0.dist-info/METADATA
django_dc_iplogger-0.3.0.dist-info/WHEEL
django_dc_iplogger-0.3.0.dist-info/top_level.txt
django_dc_iplogger-0.3.0.dist-info/RECORD
